{
    "abr320K": {"name": "320Kbps", "value": "320000", "allow":["1080p","720p"] },
    "abr256K": {"name": "256Kbps", "value": "256000", "allow":["1080p","720p","480p"]},
    "abr192K": {"name": "192Kbps", "value": "192000", "allow":["1080p","720p","480p"]},
    "abr128K": {"name": "128Kbps", "value": "128000", "allow":["1080p","720p","480p"] },
    "abr96K":  {"name": "96Kbps",  "value":  "96000", "allow":["1080p","720p","480p","360p"]},
    "abr80K":  {"name": "80Kbps",  "value":  "80000", "allow":["480p", "360p"]},
    "abr64K":  {"name": "64Kbps",  "value":  "64000", "allow":["360p", "240p"]},
    "abr32K":  {"name": "32Kbps",  "value":  "32000", "allow":["360p", "240p"]},
    "abr24K":  {"name": "24Kbps",  "value":  "24000", "allow":["240p"]}
}
